ci/environment.yml
ci/environment_hpc.yml
cstar/__init__.py
cstar/case.py
cstar/additional_files/env_files/darwin_arm64.env
cstar/additional_files/env_files/derecho.env
cstar/additional_files/env_files/expanse.env
cstar/additional_files/env_files/linux_x86.env
cstar/additional_files/env_files/perlmutter.env
cstar/additional_files/lmod_lists/derecho.lmod
cstar/additional_files/lmod_lists/expanse.lmod
cstar/additional_files/lmod_lists/perlmutter.lmod
cstar/base/__init__.py
cstar/base/additional_code.py
cstar/base/base_model.py
cstar/base/component.py
cstar/base/datasource.py
cstar/base/discretization.py
cstar/base/environment.py
cstar/base/input_dataset.py
cstar/base/system.py
cstar/base/utils.py
cstar/marbl/__init__.py
cstar/marbl/base_model.py
cstar/marbl/component.py
cstar/roms/__init__.py
cstar/roms/base_model.py
cstar/roms/component.py
cstar/roms/discretization.py
cstar/roms/input_dataset.py
cstar/tests/__init__.py
cstar/tests/integration_tests/__init__.py
cstar/tests/integration_tests/config.py
cstar/tests/integration_tests/conftest.py
cstar/tests/integration_tests/fixtures.py
cstar/tests/integration_tests/test_cstar_test_blueprints.py
cstar/tests/integration_tests/test_fixtures.py
cstar/tests/integration_tests/blueprints/__init__.py
cstar/tests/integration_tests/blueprints/cstar_blueprint_with_netcdf_datasets_template.yaml
cstar/tests/integration_tests/blueprints/cstar_blueprint_with_yaml_datasets_template.yaml
cstar/tests/integration_tests/blueprints/fixtures.py
cstar/tests/unit_tests/__init__.py
cstar/tests/unit_tests/base/__init__.py
cstar/tests/unit_tests/base/test_additional_code.py
cstar/tests/unit_tests/base/test_base_model.py
cstar/tests/unit_tests/base/test_datasource.py
cstar/tests/unit_tests/base/test_discretization.py
cstar/tests/unit_tests/base/test_environment.py
cstar/tests/unit_tests/base/test_input_dataset.py
cstar/tests/unit_tests/base/test_system.py
cstar/tests/unit_tests/base/test_utils.py
cstar/tests/unit_tests/marbl/__init__.py
cstar_ocean-0.0.7.dist-info/LICENSE
cstar_ocean-0.0.7.dist-info/METADATA
cstar_ocean-0.0.7.dist-info/WHEEL
cstar_ocean-0.0.7.dist-info/top_level.txt
cstar_ocean-0.0.7.dist-info/RECORD
