Metadata-Version: 2.2
Name: cstar-ocean
Version: 0.0.7
Summary: Computational systems for tracking ocean carbon
Author-email: Dafydd Stephenson <dafydd@cworthy.org>, Thomas Nicholas <tom@cworthy.org>, Nora Loose <nora@cworthy.org>, Matt Long <matt@cworthy.org>
License: Apache-2.0
Project-URL: repository, https://github.com/CWorthy-ocean/C-Star
Project-URL: homepage, https://www.cworthy.org
Keywords: MCDR,CDR,ocean carbon,climate
Classifier: Development Status :: 3 - Alpha
Classifier: Intended Audience :: Science/Research
Classifier: License :: OSI Approved :: Apache Software License
Classifier: Programming Language :: Python
Classifier: Programming Language :: Python :: 3.10
Classifier: Programming Language :: Python :: 3.11
Classifier: Programming Language :: Python :: 3.12
Classifier: Programming Language :: Python :: 3.13
Classifier: Topic :: Scientific/Engineering :: Oceanography
Requires-Python: >=3.10
License-File: LICENSE
Requires-Dist: python-dateutil>=2.8.2
Requires-Dist: python-dotenv
Requires-Dist: PyYAML==6.0.2
Requires-Dist: pooch>=1.8.1
Requires-Dist: roms_tools[dask]>=2.0.0
Provides-Extra: test
Requires-Dist: pytest>=7.0; extra == "test"
Requires-Dist: roms_tools[dask]==2.0.0; extra == "test"
Provides-Extra: dev
